django_ciemailfield.py
django_ci_emailfield-0.0.1.dist-info/DESCRIPTION.rst
django_ci_emailfield-0.0.1.dist-info/METADATA
django_ci_emailfield-0.0.1.dist-info/RECORD
django_ci_emailfield-0.0.1.dist-info/WHEEL
django_ci_emailfield-0.0.1.dist-info/metadata.json
django_ci_emailfield-0.0.1.dist-info/top_level.txt
