Metadata-Version: 2.0
Name: django-ci-emailfield
Version: 0.0.1
Summary: django-ci-emailfield
Provides-Extra: test
Requires-Dist: pytest (>=2.6.0); extra == 'test'
Requires-Dist: pytest-cov (>=1.7.0); extra == 'test'
